{
  "schema_version": "1.0",
  "tracks": [
    {
      "track_id": "sb_signal_to_noise",
      "title": "Signal to Noise",
      "artist": "Scott Buckley",
      "composition_family": "signal_to_noise",
      "asset_path": "music_library/tracks/sb_signal_to_noise.mp3",
      "sha256": "47a2f15ecd65f1d7ef0418ee17ae31f4e724bdf73b2c2838aaa39ac1703d094e",
      "bytes": 14143939,
      "duration_seconds": 353.541,
      "codec": "mp3",
      "source_page_url": "https://www.scottbuckley.com.au/library/signal-to-noise/",
      "license_name": "Creative Commons Attribution 4.0 International (CC BY 4.0)",
      "license_url": "https://creativecommons.org/licenses/by/4.0/",
      "attribution": "'Signal to Noise' by Scott Buckley \u2014 released under CC-BY 4.0. www.scottbuckley.com.au",
      "date_acquired": "2026-07-23T00:43:04.346Z",
      "acquisition_provenance": "Downloaded from the official Scott Buckley library (https://www.scottbuckley.com.au/library/wp-content/uploads/2020/04/sb_signaltonoise.mp3) by .github/workflows/orvyq-music-acquisition.yml; source/license page snapshot recorded at music_library/license_snapshots/sb_signal_to_noise.page.html (sha256 ac7e12fbeecb5d048822e4b3db13c98f6990841a8225541c51e7aeed8b62a1c3).",
      "approved_for_proof": true,
      "approved_for_full": true,
      "status": "approved",
      "notes": "Also assigned to CUE_06_REGULATION_PARADOX (Signal to Noise, Full Mix) in direction/music_cue_sheet.json -- the same real, already-hash-verified file, no re-acquisition needed; approved_for_full flipped to true since this asset now also backs a full-mode cue."
    },
    {
      "track_id": "sb_intervention_nomelody",
      "title": "Intervention (No Piano Melody)",
      "artist": "Scott Buckley",
      "composition_family": "intervention",
      "asset_path": "music_library/tracks/sb_intervention_nomelody.mp3",
      "sha256": "decafaf069940c9e0038c54d707a7dd27903ec91e661c1b46dbbb705c44e934c",
      "bytes": 10340546,
      "duration_seconds": 258.456,
      "codec": "mp3",
      "source_page_url": "https://www.scottbuckley.com.au/library/intervention/",
      "license_name": "Creative Commons Attribution 4.0 International (CC BY 4.0)",
      "license_url": "https://creativecommons.org/licenses/by/4.0/",
      "attribution": "'Intervention (No Piano Melody)' by Scott Buckley \u2014 released under CC-BY 4.0. www.scottbuckley.com.au",
      "date_acquired": "2026-07-23T00:42:51.918Z",
      "acquisition_provenance": "Downloaded from the official Scott Buckley library (https://www.scottbuckley.com.au/library/wp-content/uploads/2019/01/sb_intervention_nomelody.mp3) by .github/workflows/orvyq-music-acquisition.yml; source/license page snapshot recorded at music_library/license_snapshots/sb_intervention_nomelody.page.html (sha256 1e29431e0d7f1e3f4dcb14fd4cd6d628ec890ba7ad9bd52dfdf4c9c70fd9b2b9).",
      "approved_for_proof": false,
      "approved_for_full": true,
      "status": "approved"
    },
    {
      "track_id": "sb_signal_to_noise_nomelody",
      "title": "Signal to Noise (No Piano Melody)",
      "artist": "Scott Buckley",
      "composition_family": "signal_to_noise",
      "asset_path": "music_library/tracks/sb_signal_to_noise_nomelody.mp3",
      "sha256": "8e20b496b0614053565d4f43c80f469c84abd2aefb3ba01e29dfa813f49b9594",
      "bytes": 14178456,
      "duration_seconds": 354.403,
      "codec": "mp3",
      "source_page_url": "https://www.scottbuckley.com.au/library/signal-to-noise/",
      "license_name": "Creative Commons Attribution 4.0 International (CC BY 4.0)",
      "license_url": "https://creativecommons.org/licenses/by/4.0/",
      "attribution": "'Signal to Noise (No Piano Melody)' by Scott Buckley \u2014 released under CC-BY 4.0. www.scottbuckley.com.au",
      "date_acquired": "2026-07-23T00:42:53.949Z",
      "acquisition_provenance": "Downloaded from the official Scott Buckley library (https://www.scottbuckley.com.au/library/wp-content/uploads/2020/04/sb_signaltonoise_nomelody.mp3) by .github/workflows/orvyq-music-acquisition.yml; source/license page snapshot recorded at music_library/license_snapshots/sb_signal_to_noise_nomelody.page.html (sha256 d0d36db58f87499041ea54e2f21cbaad75734c14e3084fe9afd37310af8239b5).",
      "approved_for_proof": false,
      "approved_for_full": true,
      "status": "approved"
    },
    {
      "track_id": "sb_catalyst",
      "title": "Catalyst",
      "artist": "Scott Buckley",
      "composition_family": "catalyst",
      "asset_path": "music_library/tracks/sb_catalyst.mp3",
      "sha256": "8dabdc650ed2db00c9b5b685e5c9ddbc9e14e5d9f4a8dcd3f87db3ccf139e41e",
      "bytes": 11106408,
      "duration_seconds": 277.603,
      "codec": "mp3",
      "source_page_url": "https://www.scottbuckley.com.au/library/catalyst/",
      "license_name": "Creative Commons Attribution 4.0 International (CC BY 4.0)",
      "license_url": "https://creativecommons.org/licenses/by/4.0/",
      "attribution": "'Catalyst' by Scott Buckley \u2014 released under CC-BY 4.0. www.scottbuckley.com.au",
      "date_acquired": "2026-07-23T00:42:55.464Z",
      "acquisition_provenance": "Downloaded from the official Scott Buckley library (https://www.scottbuckley.com.au/library/wp-content/uploads/2020/06/sb_catalyst.mp3) by .github/workflows/orvyq-music-acquisition.yml; source/license page snapshot recorded at music_library/license_snapshots/sb_catalyst.page.html (sha256 27fabde99d3146215a55fbc8117bafa67a1b1f4f1f4eb7f977cb9990e9ae138d).",
      "approved_for_proof": false,
      "approved_for_full": true,
      "status": "approved"
    },
    {
      "track_id": "sb_emergent",
      "title": "Emergent",
      "artist": "Scott Buckley",
      "composition_family": "emergent",
      "asset_path": "music_library/tracks/sb_emergent.mp3",
      "sha256": "653e6a1e22ae7a122d7d2db87ddb3183f7bd30fe9a9ff709e93647a8f71c48e5",
      "bytes": 9247535,
      "duration_seconds": 231.131,
      "codec": "mp3",
      "source_page_url": "https://www.scottbuckley.com.au/library/emergent/",
      "license_name": "Creative Commons Attribution 4.0 International (CC BY 4.0)",
      "license_url": "https://creativecommons.org/licenses/by/4.0/",
      "attribution": "'Emergent' by Scott Buckley \u2014 released under CC-BY 4.0. www.scottbuckley.com.au",
      "date_acquired": "2026-07-23T00:42:57.301Z",
      "acquisition_provenance": "Downloaded from the official Scott Buckley library (https://www.scottbuckley.com.au/library/wp-content/uploads/2019/11/sb_emergent.mp3) by .github/workflows/orvyq-music-acquisition.yml; source/license page snapshot recorded at music_library/license_snapshots/sb_emergent.page.html (sha256 05c4fa27dc45518ac9bc96ec1626c31b2f9d0c8b44ac4f2024ec0d749001eb21).",
      "approved_for_proof": false,
      "approved_for_full": true,
      "status": "approved"
    },
    {
      "track_id": "sb_undertow",
      "title": "Undertow",
      "artist": "Scott Buckley",
      "composition_family": "undertow",
      "asset_path": "music_library/tracks/sb_undertow.mp3",
      "sha256": "4652007dad67295f1f5c87c8cbc8e2df1a530e7671266a29f693a084375d3910",
      "bytes": 10000906,
      "duration_seconds": 249.966,
      "codec": "mp3",
      "source_page_url": "https://www.scottbuckley.com.au/library/undertow/",
      "license_name": "Creative Commons Attribution 4.0 International (CC BY 4.0)",
      "license_url": "https://creativecommons.org/licenses/by/4.0/",
      "attribution": "'Undertow' by Scott Buckley \u2014 released under CC-BY 4.0. www.scottbuckley.com.au",
      "date_acquired": "2026-07-23T00:42:59.954Z",
      "acquisition_provenance": "Downloaded from the official Scott Buckley library (https://www.scottbuckley.com.au/library/wp-content/uploads/2019/12/sb_undertow.mp3) by .github/workflows/orvyq-music-acquisition.yml; source/license page snapshot recorded at music_library/license_snapshots/sb_undertow.page.html (sha256 c92277e8c6d2d224f593e2f4a9a4eac1c27ce7a3be2de364b257b7f382d8de57).",
      "approved_for_proof": false,
      "approved_for_full": true,
      "status": "approved"
    },
    {
      "track_id": "sb_ephemera",
      "title": "Ephemera",
      "artist": "Scott Buckley",
      "composition_family": "ephemera",
      "asset_path": "music_library/tracks/sb_ephemera.mp3",
      "sha256": "e38cf3aea1a9fbcc9237cc21c8fc95cdc0fdcf5fc73fc45807b46775039e77c0",
      "bytes": 13537886,
      "duration_seconds": 338.39,
      "codec": "mp3",
      "source_page_url": "https://www.scottbuckley.com.au/library/ephemera/",
      "license_name": "Creative Commons Attribution 4.0 International (CC BY 4.0)",
      "license_url": "https://creativecommons.org/licenses/by/4.0/",
      "attribution": "'Ephemera' by Scott Buckley \u2014 released under CC-BY 4.0. www.scottbuckley.com.au",
      "date_acquired": "2026-07-23T00:43:08.787Z",
      "acquisition_provenance": "Downloaded from the official Scott Buckley library (https://www.scottbuckley.com.au/library/wp-content/uploads/2020/03/sb_ephemera.mp3) by .github/workflows/orvyq-music-acquisition.yml; source/license page snapshot recorded at music_library/license_snapshots/sb_ephemera.page.html (sha256 1715984518c40e7b77488b7d2fd1451fa1b6951f8c6216cbf97bed0a4aadf834).",
      "approved_for_proof": false,
      "approved_for_full": true,
      "status": "approved"
    },
    {
      "track_id": "sb_horizons",
      "title": "Horizons",
      "artist": "Scott Buckley",
      "composition_family": "horizons",
      "asset_path": "music_library/tracks/sb_horizons.mp3",
      "sha256": "e61b3588333d284fab24411f3f7dcc495890235c49e465e33ceb072012df45c6",
      "bytes": 11738571,
      "duration_seconds": 293.407,
      "codec": "mp3",
      "source_page_url": "https://www.scottbuckley.com.au/library/horizons/",
      "license_name": "Creative Commons Attribution 4.0 International (CC BY 4.0)",
      "license_url": "https://creativecommons.org/licenses/by/4.0/",
      "attribution": "'Horizons' by Scott Buckley \u2014 released under CC-BY 4.0. www.scottbuckley.com.au",
      "date_acquired": "2026-07-23T00:43:12.739Z",
      "acquisition_provenance": "Downloaded from the official Scott Buckley library (https://www.scottbuckley.com.au/library/wp-content/uploads/2020/02/sb_horizons.mp3) by .github/workflows/orvyq-music-acquisition.yml; source/license page snapshot recorded at music_library/license_snapshots/sb_horizons.page.html (sha256 f4585affe542b945cfae100877047edc6ee8dfa1c647772cb173999119e85b3d).",
      "approved_for_proof": false,
      "approved_for_full": true,
      "status": "approved"
    },
    {
      "track_id": "sb_solace",
      "title": "Solace",
      "artist": "Scott Buckley",
      "composition_family": "solace",
      "asset_path": "music_library/tracks/sb_solace.mp3",
      "sha256": "bb54696d9b49e60d8e9edc25d80c19a975d25b3c8d8ca32afe4d963372e1d1bf",
      "bytes": 14257802,
      "duration_seconds": 356.389,
      "codec": "mp3",
      "source_page_url": "https://www.scottbuckley.com.au/library/solace/",
      "license_name": "Creative Commons Attribution 4.0 International (CC BY 4.0)",
      "license_url": "https://creativecommons.org/licenses/by/4.0/",
      "attribution": "'Solace' by Scott Buckley \u2014 released under CC-BY 4.0. www.scottbuckley.com.au",
      "date_acquired": "2026-07-23T00:43:19.291Z",
      "acquisition_provenance": "Downloaded from the official Scott Buckley library (https://www.scottbuckley.com.au/library/wp-content/uploads/2020/05/sb_solace.mp3) by .github/workflows/orvyq-music-acquisition.yml; source/license page snapshot recorded at music_library/license_snapshots/sb_solace.page.html (sha256 47dca45149eaee01e86b0585e383872442443e27bc8a49971f060d7d1ec15eb9).",
      "approved_for_proof": false,
      "approved_for_full": true,
      "status": "approved"
    }
  ]
}
